ibis/__init__.py
ibis/datastucture/__init__.py
ibis/datastucture/circuits.py
ibis/datastucture/parts.py
ibis/ingress/__init__.py
ibis/ingress/ingress.py
ibis/output/__init__.py
ibis/output/graphing.py
ibis/output/stats.py
ibis/scoring/__init__.py
ibis/scoring/scorer.py
genetic_ibis-0.2.0.dist-info/LICENSE
genetic_ibis-0.2.0.dist-info/WHEEL
genetic_ibis-0.2.0.dist-info/METADATA
genetic_ibis-0.2.0.dist-info/RECORD
